{
  "schemas": [
    {
      "type": "sqlserver",
      "name": "booktest",
      "procs": [
        {
          "type": "procedure",
          "name": "say_hello",
          "params": [
            {
              "name": "name",
              "datatype": {
                "type": "nvarchar"
              }
            }
          ],
          "return": [
            {
              "name": "result",
              "datatype": {
                "type": "nvarchar"
              }
            }
          ],
          "definition": "CREATE PROCEDURE say_hello @name NVARCHAR(255), @result NVARCHAR(255) OUTPUT AS\nBEGIN\n  SELECT @result = CONCAT('hello ', @name);\nEND;"
        }
      ],
      "tables": [
        {
          "type": "table",
          "name": "authors",
          "columns": [
            {
              "name": "author_id",
              "datatype": {
                "type": "int",
                "prec": 10
              },
              "is_primary": true,
              "is_sequence": true
            },
            {
              "name": "name",
              "datatype": {
                "type": "varchar",
                "prec": 255
              },
              "default": "('')"
            }
          ],
          "primary_keys": [
            {
              "name": "author_id",
              "datatype": {
                "type": "int",
                "prec": 10
              },
              "is_primary": true,
              "is_sequence": true
            }
          ],
          "indexes": [
            {
              "name": "authors_name_idx",
              "fields": [
                {
                  "name": "name",
                  "datatype": {
                    "type": "varchar",
                    "prec": 255
                  },
                  "default": "('')"
                }
              ]
            },
            {
              "name": "authors_pkey",
              "fields": [
                {
                  "name": "author_id",
                  "datatype": {
                    "type": "int",
                    "prec": 10
                  },
                  "is_primary": true,
                  "is_sequence": true
                }
              ],
              "is_unique": true,
              "is_primary": true
            }
          ]
        },
        {
          "type": "table",
          "name": "books",
          "columns": [
            {
              "name": "book_id",
              "datatype": {
                "type": "int",
                "prec": 10
              },
              "is_primary": true,
              "is_sequence": true
            },
            {
              "name": "author_id",
              "datatype": {
                "type": "int",
                "prec": 10
              }
            },
            {
              "name": "isbn",
              "datatype": {
                "type": "nvarchar",
                "prec": 255
              },
              "default": "('')"
            },
            {
              "name": "title",
              "datatype": {
                "type": "nvarchar",
                "prec": 255
              },
              "default": "('')"
            },
            {
              "name": "year",
              "datatype": {
                "type": "int",
                "prec": 10
              },
              "default": "((2000))"
            },
            {
              "name": "available",
              "datatype": {
                "type": "datetime2",
                "prec": 27,
                "scale": 7
              },
              "default": "(getdate())"
            },
            {
              "name": "description",
              "datatype": {
                "type": "ntext"
              },
              "default": "('')"
            },
            {
              "name": "tags",
              "datatype": {
                "type": "text"
              },
              "default": "('')"
            }
          ],
          "primary_keys": [
            {
              "name": "book_id",
              "datatype": {
                "type": "int",
                "prec": 10
              },
              "is_primary": true,
              "is_sequence": true
            }
          ],
          "indexes": [
            {
              "name": "books_isbn_key",
              "fields": [
                {
                  "name": "isbn",
                  "datatype": {
                    "type": "nvarchar",
                    "prec": 255
                  },
                  "default": "('')"
                }
              ],
              "is_unique": true
            },
            {
              "name": "books_pkey",
              "fields": [
                {
                  "name": "book_id",
                  "datatype": {
                    "type": "int",
                    "prec": 10
                  },
                  "is_primary": true,
                  "is_sequence": true
                }
              ],
              "is_unique": true,
              "is_primary": true
            },
            {
              "name": "books_title_idx",
              "fields": [
                {
                  "name": "title",
                  "datatype": {
                    "type": "nvarchar",
                    "prec": 255
                  },
                  "default": "('')"
                },
                {
                  "name": "year",
                  "datatype": {
                    "type": "int",
                    "prec": 10
                  },
                  "default": "((2000))"
                }
              ]
            }
          ],
          "foreign_keys": [
            {
              "name": "books_author_id_fkey",
              "column": [
                {
                  "name": "author_id",
                  "datatype": {
                    "type": "int",
                    "prec": 10
                  }
                }
              ],
              "ref_table": "authors",
              "ref_column": [
                {
                  "name": "author_id",
                  "datatype": {
                    "type": "int",
                    "prec": 10
                  },
                  "is_primary": true,
                  "is_sequence": true
                }
              ]
            }
          ]
        }
      ]
    }
  ]
}
